odoo/addons/purchase_report_extension/README.rst
odoo/addons/purchase_report_extension/__init__.py
odoo/addons/purchase_report_extension/__manifest__.py
odoo/addons/purchase_report_extension/i18n/es.po
odoo/addons/purchase_report_extension/i18n/purchase_report_extension.pot
odoo/addons/purchase_report_extension/readme/CONTRIBUTORS.rst
odoo/addons/purchase_report_extension/readme/DESCRIPTION.rst
odoo/addons/purchase_report_extension/readme/ROADMAP.rst
odoo/addons/purchase_report_extension/reports/__init__.py
odoo/addons/purchase_report_extension/reports/purchase_report.py
odoo/addons/purchase_report_extension/static/description/icon.png
odoo/addons/purchase_report_extension/static/description/index.html
odoo12_addon_purchase_report_extension-12.0.1.0.0.99.dev7.dist-info/METADATA
odoo12_addon_purchase_report_extension-12.0.1.0.0.99.dev7.dist-info/WHEEL
odoo12_addon_purchase_report_extension-12.0.1.0.0.99.dev7.dist-info/top_level.txt
odoo12_addon_purchase_report_extension-12.0.1.0.0.99.dev7.dist-info/RECORD
